annotell_openlabel-0.1.4-py3.9-nspkg.pth
annotell/openlabel/__init__.py
annotell/openlabel/models/__init__.py
annotell/openlabel/models/models.py
annotell/openlabel/models/utils/__init__.py
annotell/openlabel/models/utils/data_type_parsing.py
annotell/openlabel/schemas/__init__.py
annotell/openlabel/schemas/openlabel-1-0-0-edited.json
annotell/openlabel/schemas/openlabel-1-0-0.json
annotell/openlabel/tools/__init__.py
annotell/openlabel/tools/model_generation.py
annotell_openlabel-0.1.4.dist-info/METADATA
annotell_openlabel-0.1.4.dist-info/WHEEL
annotell_openlabel-0.1.4.dist-info/namespace_packages.txt
annotell_openlabel-0.1.4.dist-info/top_level.txt
annotell_openlabel-0.1.4.dist-info/RECORD
