Metadata-Version: 2.1
Name: annotell-openlabel
Version: 0.1.4
Summary: Annotell OpenLABEL Datamodel
Home-page: https://github.com/annotell/annotell-python
Author: Annotell
Author-email: Interoperability <interoperability@annotell.com>
License: MIT
Download-URL: https://github.com/annotell/annotell-python/tarball/0.1.4
Keywords: Annotell,OpenLABEL
Platform: UNKNOWN
Classifier: Development Status :: 3 - Alpha
Classifier: License :: OSI Approved :: MIT License
Classifier: Intended Audience :: Developers
Classifier: Programming Language :: Python :: 3
Requires-Python: >=3.6
